mayacalendar.py
mayacalendar-2.0.0.dist-info/licenses/LICENSE
mayacalendar-2.0.0.dist-info/METADATA
mayacalendar-2.0.0.dist-info/WHEEL
mayacalendar-2.0.0.dist-info/top_level.txt
mayacalendar-2.0.0.dist-info/RECORD
