Metadata-Version: 2.4
Name: MayaCalendar
Version: 2.0.0
Summary: Maya Calendar convertor (Long Count, Tzolkin, Haab).
Author-email: Nicolas Flandrois <contacts@flandrois.com>
Maintainer-email: Nicolas Flandrois <nicolas.dev@flandrois.com>
License:                     GNU GENERAL PUBLIC LICENSE
Project-URL: Homepage, https://github.com/NicolasFlandrois/Maya-Calendar-Python-Package
Project-URL: GitHub, https://github.com/NicolasFlandrois/Maya-Calendar-Python-Package
Keywords: maya,calendar,datetime,convertor
Classifier: Programming Language :: Python :: 3
Classifier: License :: OSI Approved :: GNU General Public License v3 (GPLv3)
Classifier: Operating System :: OS Independent
Requires-Python: >=3.14
License-File: LICENSE
Dynamic: license-file
